LICENSE
MANIFEST.in
README.md
ghetto.py
setup.py
ghetto.egg-info/PKG-INFO
ghetto.egg-info/SOURCES.txt
ghetto.egg-info/dependency_links.txt
ghetto.egg-info/entry_points.txt
ghetto.egg-info/top_level.txt