Metadata-Version: 1.1
Name: ghetto
Version: 0.1.0
Summary: A tool for (automatized) torrent files downloading from RSS feeds.
Home-page: https://github.com/infinite-library/ghetto
Author: Nikita K.
Author-email: mendor@yuuzukiyo.net
License: MIT
Keywords: ghetto torrent bittorrent rss
Platform: UNKNOWN
Classifier: Development Status :: 3 - Alpha
Classifier: Environment :: Console
Classifier: Intended Audience :: Information Technology
Classifier: License :: OSI Approved :: MIT License
Classifier: Operating System :: MacOS :: MacOS X
Classifier: Operating System :: POSIX :: Linux
Classifier: Programming Language :: Python :: 2
Classifier: Programming Language :: Python :: 2 :: Only
Classifier: Topic :: Utilities
